nanda_agent/__init__.py
nanda_agent/cli.py
nanda_agent/core/__init__.py
nanda_agent/core/agent_bridge.py
nanda_agent/core/mcp_utils.py
nanda_agent/core/nanda.py
nanda_agent/core/registry_url.txt
nanda_agent/core/run_ui_agent_https.py
nanda_agent/examples/crewai_sarcastic.py
nanda_agent/examples/langchain_pirate.py
nanda_agent/examples/requirements.txt
nanda_agent-1.0.5.dist-info/METADATA
nanda_agent-1.0.5.dist-info/WHEEL
nanda_agent-1.0.5.dist-info/entry_points.txt
nanda_agent-1.0.5.dist-info/top_level.txt
nanda_agent-1.0.5.dist-info/RECORD
