Metadata-Version: 2.4
Name: nanda-agent
Version: 1.0.5
Summary: Customizable AI Agent Communication Framework with pluggable message improvement logic
Home-page: https://github.com/aidecentralized/nanda-agent-sdk.git
Author: NANDA Team
Author-email: support@nanda.ai
Keywords: nanda ai agent framework
Classifier: Development Status :: 4 - Beta
Classifier: Intended Audience :: Developers
Classifier: Topic :: Software Development :: Libraries :: Python Modules
Classifier: Topic :: Scientific/Engineering :: Artificial Intelligence
Classifier: License :: OSI Approved :: MIT License
Classifier: Programming Language :: Python :: 3
Classifier: Programming Language :: Python :: 3.8
Classifier: Programming Language :: Python :: 3.9
Classifier: Programming Language :: Python :: 3.10
Classifier: Programming Language :: Python :: 3.11
Classifier: Programming Language :: Python :: 3.12
Requires-Python: >=3.8
Requires-Dist: flask
Requires-Dist: anthropic
Requires-Dist: requests
Requires-Dist: python-a2a==0.5.6
Requires-Dist: mcp
Requires-Dist: python-dotenv
Requires-Dist: flask-cors
Requires-Dist: pymongo
Provides-Extra: langchain
Requires-Dist: langchain-core; extra == "langchain"
Requires-Dist: langchain-anthropic; extra == "langchain"
Provides-Extra: crewai
Requires-Dist: crewai; extra == "crewai"
Requires-Dist: langchain-anthropic; extra == "crewai"
Provides-Extra: all
Requires-Dist: langchain-core; extra == "all"
Requires-Dist: langchain-anthropic; extra == "all"
Requires-Dist: crewai; extra == "all"
Dynamic: author
Dynamic: author-email
Dynamic: classifier
Dynamic: description
Dynamic: description-content-type
Dynamic: home-page
Dynamic: keywords
Dynamic: provides-extra
Dynamic: requires-dist
Dynamic: requires-python
Dynamic: summary
